LICENSE
README.md
setup.py
torboost/__init__.py
torboost/torboost.py
torboost.egg-info/PKG-INFO
torboost.egg-info/SOURCES.txt
torboost.egg-info/dependency_links.txt
torboost.egg-info/entry_points.txt
torboost.egg-info/requires.txt
torboost.egg-info/top_level.txt