Metadata-Version: 2.1
Name: torboost
Version: 0.9.3
Summary: Download utility for Tor
Home-page: https://github.com/tasooshi/torboost/
Author: tasooshi
Author-email: tasooshi@pm.me
License: MIT License
Keywords: Tor,onion,download
Platform: UNKNOWN
Classifier: Development Status :: 4 - Beta
Classifier: Topic :: Utilities
Classifier: License :: OSI Approved :: MIT License
Classifier: Programming Language :: Python :: 3.9
Classifier: Programming Language :: Python :: 3.10
License-File: LICENSE
